aws_cost_optimization_5/__init__.py
aws_cost_optimization_5/_ri_recommendations.py
aws_cost_optimization_5/_savings_plan.py
aws_cost_optimization_5/utils.py
aws_cost_optimization_5-0.1.8.dist-info/LICENCE
aws_cost_optimization_5-0.1.8.dist-info/METADATA
aws_cost_optimization_5-0.1.8.dist-info/WHEEL
aws_cost_optimization_5-0.1.8.dist-info/top_level.txt
aws_cost_optimization_5-0.1.8.dist-info/RECORD
