Metadata-Version: 2.1
Name: aws_cost_optimization_5
Version: 0.1.8
Summary: Provides AWS cost recommendations
Author-email: "dheeraj.banodha" <dheeraj.banodha@impetus.com>
Classifier: Programming Language :: Python :: 3
Classifier: Operating System :: OS Independent
Requires-Python: >=3.10
License-File: LICENCE
